MANIFEST.in
ez_setup.py
pip-requirements
rtd-pip-requirements
setup.py
docs/Makefile
docs/README
docs/_doctemplate.rst
docs/about.rst
docs/changelog.rst
docs/conf.py
docs/development.rst
docs/extensions.rst
docs/index.rst
docs/install.rst
docs/make.bat
docs/research.rst
docs/support.rst
docs/_static/ex_lbfgs15.png
docs/_static/ex_marm_obj.png
docs/_static/ex_marm_recon.png
docs/_static/ex_reflector.png
docs/_static/exercises/p1_1.png
docs/_static/exercises/p1_5.png
docs/_static/exercises/p1_7.png
docs/_static/exercises/p2_3.png
docs/api/pysit.core.acquisition.equispaced_acquisition.rst
docs/api/pysit.core.domain.Dirichlet.rst
docs/api/pysit.core.domain.DomainBC.rst
docs/api/pysit.core.domain.DomainBase.rst
docs/api/pysit.core.domain.Neumann.rst
docs/api/pysit.core.domain.PML.rst
docs/api/pysit.core.domain.RectangularDomain.rst
docs/api/pysit.core.mesh.CartesianMesh.rst
docs/api/pysit.core.mesh.StructuredDirichlet.rst
docs/api/pysit.core.mesh.StructuredNeumann.rst
docs/api/pysit.core.mesh.StructuredPML.rst
docs/api/pysit.core.mesh_representation.MeshRepresentationBase.rst
docs/api/pysit.core.mesh_representation.PointRepresentationBase.rst
docs/api/pysit.core.receivers.PointReceiver.rst
docs/api/pysit.core.receivers.ReceiverSet.rst
docs/api/pysit.core.shot.Shot.rst
docs/api/pysit.core.sources.PointSource.rst
docs/api/pysit.core.sources.SourceSet.rst
docs/api/pysit.core.wave_source.DerivativeGaussianPulse.rst
docs/api/pysit.core.wave_source.GaussianPulse.rst
docs/api/pysit.core.wave_source.RickerWavelet.rst
docs/api/pysit.core.wave_source.SourceWaveletBase.rst
docs/api/pysit.core.wave_source.WhiteNoiseSource.rst
docs/api/pysit.gallery.bp.BPModel.rst
docs/api/pysit.gallery.bp.bp.rst
docs/api/pysit.gallery.horizontal_reflector.HorizontalReflectorModel.rst
docs/api/pysit.gallery.horizontal_reflector.horizontal_reflector.rst
docs/api/pysit.gallery.layered_medium.Layer.rst
docs/api/pysit.gallery.layered_medium.LayeredMediumModel.rst
pysit.egg-info/PKG-INFO
pysit.egg-info/SOURCES.txt
pysit.egg-info/dependency_links.txt
pysit.egg-info/requires.txt
pysit.egg-info/top_level.txt
