Metadata-Version: 1.1
Name: pysit
Version: 0.5b3
Summary: PySIT: Seismic Imaging Toolbox in Python
Home-page: http://www.pysit.org/
Author: Russell J. Hewett
Author-email: rhewett@mit.edu
License: BSD
Download-URL: http://www.pysit.org/
Keywords: seismic inverse problem imaging
Platform: Windows
Platform: Linux
Platform: Solaris
Platform: Mac OS-X
Platform: Unix
Classifier: Development Status :: 4 - Beta
Classifier: Intended Audience :: Science/Research
Classifier: Intended Audience :: Developers
Classifier: License :: OSI Approved :: BSD License
Classifier: Programming Language :: C++
Classifier: Programming Language :: Python
Classifier: Topic :: Scientific/Engineering
Classifier: Topic :: Scientific/Engineering :: Mathematics
Classifier: Operating System :: Microsoft :: Windows
Classifier: Operating System :: POSIX
Classifier: Operating System :: Unix
Classifier: Operating System :: MacOS
